test/__init__.py
webullpaysdktradeeventscore/__init__.py
webullpaysdktradeeventscore/default_retry_policy.py
webullpaysdktradeeventscore/events_client.py
webullpaysdktradeeventscore/events_pb2.py
webullpaysdktradeeventscore/events_pb2_grpc.py
webullpaysdktradeeventscore/signature_composer.py
webullpay_python_sdk_trade_events_core-0.1.0.dist-info/METADATA
webullpay_python_sdk_trade_events_core-0.1.0.dist-info/WHEEL
webullpay_python_sdk_trade_events_core-0.1.0.dist-info/top_level.txt
webullpay_python_sdk_trade_events_core-0.1.0.dist-info/RECORD
